introsort_multithreaded/__init__.py
introsort_multithreaded/sorting_eleven/__init__.py
introsort_multithreaded/sorting_eleven/sorting.pyd
introsort_multithreaded/sorting_twelve/__init__.py
introsort_multithreaded/sorting_twelve/sorting.pyd
introsort_multithreaded-0.0.7.dist-info/LICENCE.txt
introsort_multithreaded-0.0.7.dist-info/METADATA
introsort_multithreaded-0.0.7.dist-info/WHEEL
introsort_multithreaded-0.0.7.dist-info/top_level.txt
introsort_multithreaded-0.0.7.dist-info/RECORD
