Metadata-Version: 2.1
Name: introsort_multithreaded
Version: 0.0.7
Summary: multithreaded introsort
Author: Chong Yih Yang
Author-email: chongyihyang713@gmail.com
License: MIT
Keywords: sorting
Classifier: Development Status :: 5 - Production/Stable
Classifier: Intended Audience :: Education
Classifier: Operating System :: Microsoft :: Windows :: Windows 10
Classifier: License :: OSI Approved :: MIT License
Classifier: Programming Language :: Python :: 3
Requires-Python: >=3.11.0
License-File: LICENCE.txt
